{
    "NODES": {
        "connector_1_1": [
            150.0,
            140.0
        ],
        "connector_1_2": [
            100.0,
            100.0
        ],
        "connector_1_3": [
            70.0,
            150.0
        ],
        "connector_2_2": [
            250.0,
            250.0
        ],
        "connector_2_3": [
            260.0,
            280.0
        ],
        "dump_hub_1a": [
            180.0,
            280.0
        ],
        "dump_hub_1b": [
            200.0,
            280.0
        ],
        "dump_spur_1a_1": [
            190.0,
            310.0
        ],
        "dump_spur_1a_2": [
            180.0,
            320.0
        ],
        "dump_spur_1b_1": [
            210.0,
            310.0
        ],
        "dump_spur_1b_2": [
            220.0,
            320.0
        ],
        "dump_zone_1": [
            180.0,
            340.0
        ],
        "dump_zone_10": [
            700.0,
            320.0
        ],
        "dump_zone_11": [
            750.0,
            320.0
        ],
        "dump_zone_12": [
            650.0,
            370.0
        ],
        "dump_zone_13": [
            700.0,
            370.0
        ],
        "dump_zone_14": [
            750.0,
            370.0
        ],
        "dump_zone_15": [
            50.0,
            740.0
        ],
        "dump_zone_16": [
            150.0,
            790.0
        ],
        "dump_zone_17": [
            250.0,
            740.0
        ],
        "dump_zone_18": [
            -50.0,
            740.0
        ],
        "dump_zone_19": [
            50.0,
            840.0
        ],
        "dump_zone_2": [
            220.0,
            340.0
        ],
        "dump_zone_20": [
            250.0,
            840.0
        ],
        "dump_zone_21": [
            350.0,
            740.0
        ],
        "dump_zone_22": [
            -170.0,
            450.0
        ],
        "dump_zone_23": [
            -100.0,
            520.0
        ],
        "dump_zone_24": [
            -30.0,
            450.0
        ],
        "dump_zone_3": [
            650.0,
            180.0
        ],
        "dump_zone_4": [
            700.0,
            180.0
        ],
        "dump_zone_5": [
            750.0,
            180.0
        ],
        "dump_zone_6": [
            650.0,
            130.0
        ],
        "dump_zone_7": [
            700.0,
            130.0
        ],
        "dump_zone_8": [
            750.0,
            130.0
        ],
        "dump_zone_9": [
            650.0,
            320.0
        ],
        "e_connector_n": [
            750.0,
            225.0
        ],
        "e_connector_s": [
            750.0,
            275.0
        ],
        "e_grid_1_a": [
            600.0,
            200.0
        ],
        "e_grid_1_b": [
            650.0,
            200.0
        ],
        "e_grid_1_c": [
            700.0,
            200.0
        ],
        "e_grid_1_d": [
            750.0,
            200.0
        ],
        "e_grid_2_a": [
            600.0,
            150.0
        ],
        "e_grid_2_b": [
            650.0,
            150.0
        ],
        "e_grid_2_c": [
            700.0,
            150.0
        ],
        "e_grid_2_d": [
            750.0,
            150.0
        ],
        "e_grid_3_a": [
            600.0,
            300.0
        ],
        "e_grid_3_b": [
            650.0,
            300.0
        ],
        "e_grid_3_c": [
            700.0,
            300.0
        ],
        "e_grid_3_d": [
            750.0,
            300.0
        ],
        "e_grid_4_a": [
            600.0,
            350.0
        ],
        "e_grid_4_b": [
            650.0,
            350.0
        ],
        "e_grid_4_c": [
            700.0,
            350.0
        ],
        "e_grid_4_d": [
            750.0,
            350.0
        ],
        "e_haul_1": [
            300.0,
            250.0
        ],
        "e_haul_2": [
            400.0,
            250.0
        ],
        "e_haul_3": [
            500.0,
            250.0
        ],
        "e_hub": [
            600.0,
            250.0
        ],
        "fuel_1": [
            700.0,
            630.0
        ],
        "fuel_2": [
            700.0,
            670.0
        ],
        "fw_haul_1": [
            -50.0,
            250.0
        ],
        "fw_haul_2": [
            -150.0,
            250.0
        ],
        "fw_haul_3": [
            -250.0,
            250.0
        ],
        "fw_hub": [
            -350.0,
            250.0
        ],
        "fw_load_spur_1": [
            -470.0,
            150.0
        ],
        "fw_load_spur_10": [
            -600.0,
            270.0
        ],
        "fw_load_spur_11": [
            -550.0,
            470.0
        ],
        "fw_load_spur_12": [
            -200.0,
            420.0
        ],
        "fw_load_spur_2": [
            -500.0,
            270.0
        ],
        "fw_load_spur_3": [
            -450.0,
            370.0
        ],
        "fw_load_spur_4": [
            -300.0,
            320.0
        ],
        "fw_load_spur_5": [
            -520.0,
            100.0
        ],
        "fw_load_spur_6": [
            -550.0,
            270.0
        ],
        "fw_load_spur_7": [
            -500.0,
            420.0
        ],
        "fw_load_spur_8": [
            -250.0,
            370.0
        ],
        "fw_load_spur_9": [
            -570.0,
            50.0
        ],
        "fw_pit_1_a": [
            -350.0,
            150.0
        ],
        "fw_pit_1_b": [
            -450.0,
            150.0
        ],
        "fw_pit_1_c": [
            -500.0,
            250.0
        ],
        "fw_pit_1_d": [
            -450.0,
            350.0
        ],
        "fw_pit_1_e": [
            -350.0,
            350.0
        ],
        "fw_pit_1_f": [
            -300.0,
            300.0
        ],
        "fw_pit_1_g": [
            -300.0,
            200.0
        ],
        "fw_pit_2_a": [
            -350.0,
            100.0
        ],
        "fw_pit_2_b": [
            -500.0,
            100.0
        ],
        "fw_pit_2_c": [
            -550.0,
            250.0
        ],
        "fw_pit_2_d": [
            -500.0,
            400.0
        ],
        "fw_pit_2_e": [
            -350.0,
            400.0
        ],
        "fw_pit_2_f": [
            -250.0,
            350.0
        ],
        "fw_pit_2_g": [
            -250.0,
            150.0
        ],
        "fw_pit_3_a": [
            -350.0,
            50.0
        ],
        "fw_pit_3_b": [
            -550.0,
            50.0
        ],
        "fw_pit_3_c": [
            -600.0,
            250.0
        ],
        "fw_pit_3_d": [
            -550.0,
            450.0
        ],
        "fw_pit_3_e": [
            -350.0,
            450.0
        ],
        "fw_pit_3_f": [
            -200.0,
            400.0
        ],
        "fw_pit_3_g": [
            -200.0,
            100.0
        ],
        "ix_east_1": [
            180.0,
            250.0
        ],
        "ix_east_2": [
            200.0,
            250.0
        ],
        "ix_north_1": [
            150.0,
            220.0
        ],
        "ix_north_2": [
            150.0,
            200.0
        ],
        "ix_west_1": [
            120.0,
            250.0
        ],
        "ix_west_2": [
            100.0,
            250.0
        ],
        "load_hub_1a": [
            120.0,
            200.0
        ],
        "load_hub_1b": [
            100.0,
            200.0
        ],
        "load_hub_2a": [
            180.0,
            200.0
        ],
        "load_hub_2b": [
            200.0,
            200.0
        ],
        "load_spur_1a_1": [
            90.0,
            190.0
        ],
        "load_spur_1a_2": [
            80.0,
            180.0
        ],
        "load_spur_1b_1": [
            110.0,
            190.0
        ],
        "load_spur_1b_2": [
            120.0,
            180.0
        ],
        "load_spur_2a_1": [
            190.0,
            170.0
        ],
        "load_spur_2a_2": [
            180.0,
            150.0
        ],
        "load_spur_2b_1": [
            210.0,
            170.0
        ],
        "load_spur_2b_2": [
            220.0,
            150.0
        ],
        "load_zone_1": [
            80.0,
            160.0
        ],
        "load_zone_10": [
            -500.0,
            440.0
        ],
        "load_zone_11": [
            -250.0,
            390.0
        ],
        "load_zone_12": [
            -590.0,
            50.0
        ],
        "load_zone_13": [
            -600.0,
            290.0
        ],
        "load_zone_14": [
            -550.0,
            490.0
        ],
        "load_zone_15": [
            -200.0,
            440.0
        ],
        "load_zone_16": [
            50.0,
            -290.0
        ],
        "load_zone_17": [
            150.0,
            -340.0
        ],
        "load_zone_18": [
            250.0,
            -290.0
        ],
        "load_zone_19": [
            0.0,
            -290.0
        ],
        "load_zone_2": [
            120.0,
            160.0
        ],
        "load_zone_20": [
            150.0,
            -390.0
        ],
        "load_zone_21": [
            300.0,
            -290.0
        ],
        "load_zone_22": [
            -170.0,
            400.0
        ],
        "load_zone_23": [
            -100.0,
            330.0
        ],
        "load_zone_24": [
            500.0,
            -190.0
        ],
        "load_zone_25": [
            600.0,
            -240.0
        ],
        "load_zone_26": [
            700.0,
            -190.0
        ],
        "load_zone_27": [
            450.0,
            -190.0
        ],
        "load_zone_28": [
            600.0,
            -290.0
        ],
        "load_zone_29": [
            750.0,
            -190.0
        ],
        "load_zone_3": [
            200.0,
            120.0
        ],
        "load_zone_4": [
            -490.0,
            150.0
        ],
        "load_zone_5": [
            -500.0,
            290.0
        ],
        "load_zone_6": [
            -450.0,
            390.0
        ],
        "load_zone_7": [
            -300.0,
            340.0
        ],
        "load_zone_8": [
            -540.0,
            100.0
        ],
        "load_zone_9": [
            -550.0,
            290.0
        ],
        "main_hub": [
            150.0,
            250.0
        ],
        "n_haul_1": [
            150.0,
            100.0
        ],
        "n_haul_2": [
            150.0,
            0.0
        ],
        "n_haul_3": [
            150.0,
            -100.0
        ],
        "n_hub": [
            150.0,
            -200.0
        ],
        "n_load_spur_1": [
            50.0,
            -270.0
        ],
        "n_load_spur_2": [
            150.0,
            -320.0
        ],
        "n_load_spur_3": [
            250.0,
            -270.0
        ],
        "n_load_spur_4": [
            0.0,
            -270.0
        ],
        "n_load_spur_5": [
            150.0,
            -370.0
        ],
        "n_load_spur_6": [
            300.0,
            -270.0
        ],
        "n_q_1_a": [
            100.0,
            -200.0
        ],
        "n_q_1_b": [
            50.0,
            -250.0
        ],
        "n_q_1_c": [
            100.0,
            -300.0
        ],
        "n_q_1_d": [
            200.0,
            -300.0
        ],
        "n_q_1_e": [
            250.0,
            -250.0
        ],
        "n_q_1_f": [
            200.0,
            -200.0
        ],
        "n_q_2_a": [
            50.0,
            -200.0
        ],
        "n_q_2_b": [
            0.0,
            -250.0
        ],
        "n_q_2_c": [
            50.0,
            -350.0
        ],
        "n_q_2_d": [
            250.0,
            -350.0
        ],
        "n_q_2_e": [
            300.0,
            -250.0
        ],
        "n_q_2_f": [
            250.0,
            -200.0
        ],
        "ne_haul_1": [
            600.0,
            100.0
        ],
        "ne_haul_2": [
            600.0,
            0.0
        ],
        "ne_hub": [
            600.0,
            -100.0
        ],
        "ne_load_spur_1": [
            500.0,
            -170.0
        ],
        "ne_load_spur_2": [
            600.0,
            -220.0
        ],
        "ne_load_spur_3": [
            700.0,
            -170.0
        ],
        "ne_load_spur_4": [
            450.0,
            -170.0
        ],
        "ne_load_spur_5": [
            600.0,
            -270.0
        ],
        "ne_load_spur_6": [
            750.0,
            -170.0
        ],
        "ne_q_1_a": [
            550.0,
            -100.0
        ],
        "ne_q_1_b": [
            500.0,
            -150.0
        ],
        "ne_q_1_c": [
            550.0,
            -200.0
        ],
        "ne_q_1_d": [
            650.0,
            -200.0
        ],
        "ne_q_1_e": [
            700.0,
            -150.0
        ],
        "ne_q_1_f": [
            650.0,
            -100.0
        ],
        "ne_q_2_a": [
            500.0,
            -100.0
        ],
        "ne_q_2_b": [
            450.0,
            -150.0
        ],
        "ne_q_2_c": [
            500.0,
            -250.0
        ],
        "ne_q_2_d": [
            700.0,
            -250.0
        ],
        "ne_q_2_e": [
            750.0,
            -150.0
        ],
        "ne_q_2_f": [
            700.0,
            -100.0
        ],
        "parking_1": [
            500.0,
            630.0
        ],
        "parking_2": [
            500.0,
            670.0
        ],
        "purple_auto_3": [
            150.8,
            489.6
        ],
        "purple_auto_fix_1": [
            80.0,
            166.7
        ],
        "purple_auto_fix_2": [
            -200.0,
            250.0
        ],
        "purple_auto_fix_3": [
            -300.0,
            250.0
        ],
        "s_connector_1": [
            0.0,
            550.0
        ],
        "s_connector_2": [
            -50.0,
            450.0
        ],
        "s_dump_spur_1": [
            50.0,
            720.0
        ],
        "s_dump_spur_2": [
            150.0,
            770.0
        ],
        "s_dump_spur_3": [
            250.0,
            720.0
        ],
        "s_dump_spur_4": [
            -50.0,
            720.0
        ],
        "s_dump_spur_5": [
            50.0,
            820.0
        ],
        "s_dump_spur_6": [
            250.0,
            820.0
        ],
        "s_dump_spur_7": [
            350.0,
            720.0
        ],
        "s_haul_1": [
            150.0,
            350.0
        ],
        "s_haul_2": [
            150.0,
            450.0
        ],
        "s_haul_3": [
            150.0,
            550.0
        ],
        "s_hub": [
            150.0,
            650.0
        ],
        "s_sp_1_a": [
            100.0,
            650.0
        ],
        "s_sp_1_b": [
            50.0,
            700.0
        ],
        "s_sp_1_c": [
            100.0,
            750.0
        ],
        "s_sp_1_d": [
            200.0,
            750.0
        ],
        "s_sp_1_e": [
            250.0,
            700.0
        ],
        "s_sp_1_f": [
            200.0,
            650.0
        ],
        "s_sp_2_a": [
            0.0,
            650.0
        ],
        "s_sp_2_b": [
            -50.0,
            700.0
        ],
        "s_sp_2_c": [
            0.0,
            750.0
        ],
        "s_sp_2_d": [
            100.0,
            800.0
        ],
        "s_sp_2_e": [
            200.0,
            800.0
        ],
        "s_sp_2_f": [
            300.0,
            750.0
        ],
        "s_sp_2_g": [
            350.0,
            700.0
        ],
        "s_sp_2_h": [
            300.0,
            650.0
        ],
        "service_exit_1": [
            150.0,
            280.0
        ],
        "service_exit_2": [
            160.0,
            270.0
        ],
        "service_haul_1": [
            600.0,
            400.0
        ],
        "service_haul_2": [
            600.0,
            500.0
        ],
        "service_hub": [
            600.0,
            600.0
        ],
        "service_loop_1": [
            550.0,
            600.0
        ],
        "service_loop_2": [
            500.0,
            650.0
        ],
        "service_loop_3": [
            550.0,
            700.0
        ],
        "service_loop_4": [
            650.0,
            700.0
        ],
        "service_loop_5": [
            700.0,
            650.0
        ],
        "service_loop_6": [
            650.0,
            600.0
        ],
        "start_zone": [
            150.0,
            300.0
        ],
        "sw_connector_1": [
            -100.0,
            400.0
        ],
        "sw_connector_2": [
            -50.0,
            350.0
        ],
        "sw_dump_spur_1": [
            -150.0,
            450.0
        ],
        "sw_dump_spur_2": [
            -100.0,
            500.0
        ],
        "sw_dump_spur_3": [
            -50.0,
            450.0
        ],
        "sw_haul_1": [
            100.0,
            300.0
        ],
        "sw_haul_2": [
            50.0,
            350.0
        ],
        "sw_haul_3": [
            0.0,
            400.0
        ],
        "sw_hub": [
            -100.0,
            450.0
        ],
        "sw_load_spur_1": [
            -150.0,
            400.0
        ],
        "sw_load_spur_2": [
            -100.0,
            350.0
        ]
    },
    "EDGES": [
        [
            "connector_1_1",
            "connector_1_2"
        ],
        [
            "connector_1_1",
            "n_haul_1"
        ],
        [
            "connector_1_2",
            "connector_1_3"
        ],
        [
            "connector_1_3",
            "purple_auto_fix_1"
        ],
        [
            "connector_2_2",
            "connector_2_3"
        ],
        [
            "connector_2_2",
            "e_haul_1"
        ],
        [
            "connector_2_2",
            "ix_east_2"
        ],
        [
            "connector_2_3",
            "dump_zone_2"
        ],
        [
            "dump_hub_1a",
            "dump_hub_1b"
        ],
        [
            "dump_hub_1a",
            "s_haul_1"
        ],
        [
            "dump_hub_1b",
            "dump_spur_1a_1"
        ],
        [
            "dump_hub_1b",
            "dump_spur_1b_1"
        ],
        [
            "dump_spur_1a_1",
            "dump_spur_1a_2"
        ],
        [
            "dump_spur_1a_2",
            "dump_zone_1"
        ],
        [
            "dump_spur_1b_1",
            "dump_spur_1b_2"
        ],
        [
            "dump_spur_1b_2",
            "dump_zone_2"
        ],
        [
            "e_connector_n",
            "e_connector_s"
        ],
        [
            "e_grid_1_a",
            "e_grid_1_b"
        ],
        [
            "e_grid_1_a",
            "e_grid_2_a"
        ],
        [
            "e_grid_1_a",
            "ne_haul_1"
        ],
        [
            "e_grid_1_b",
            "dump_zone_3"
        ],
        [
            "e_grid_1_b",
            "e_grid_1_c"
        ],
        [
            "e_grid_1_b",
            "e_grid_2_b"
        ],
        [
            "e_grid_1_c",
            "dump_zone_4"
        ],
        [
            "e_grid_1_c",
            "e_grid_1_d"
        ],
        [
            "e_grid_1_c",
            "e_grid_2_c"
        ],
        [
            "e_grid_1_d",
            "dump_zone_5"
        ],
        [
            "e_grid_1_d",
            "e_connector_n"
        ],
        [
            "e_grid_1_d",
            "e_grid_2_d"
        ],
        [
            "e_grid_2_a",
            "e_grid_2_b"
        ],
        [
            "e_grid_2_b",
            "dump_zone_6"
        ],
        [
            "e_grid_2_b",
            "e_grid_2_c"
        ],
        [
            "e_grid_2_c",
            "dump_zone_7"
        ],
        [
            "e_grid_2_c",
            "e_grid_2_d"
        ],
        [
            "e_grid_2_d",
            "dump_zone_8"
        ],
        [
            "e_grid_2_d",
            "e_connector_n"
        ],
        [
            "e_grid_3_a",
            "e_grid_3_b"
        ],
        [
            "e_grid_3_a",
            "e_grid_4_a"
        ],
        [
            "e_grid_3_b",
            "dump_zone_9"
        ],
        [
            "e_grid_3_b",
            "e_grid_3_c"
        ],
        [
            "e_grid_3_b",
            "e_grid_4_b"
        ],
        [
            "e_grid_3_c",
            "dump_zone_10"
        ],
        [
            "e_grid_3_c",
            "e_grid_3_d"
        ],
        [
            "e_grid_3_c",
            "e_grid_4_c"
        ],
        [
            "e_grid_3_d",
            "dump_zone_11"
        ],
        [
            "e_grid_3_d",
            "e_connector_s"
        ],
        [
            "e_grid_3_d",
            "e_grid_4_d"
        ],
        [
            "e_grid_4_a",
            "e_grid_4_b"
        ],
        [
            "e_grid_4_a",
            "service_haul_1"
        ],
        [
            "e_grid_4_b",
            "dump_zone_12"
        ],
        [
            "e_grid_4_b",
            "e_grid_4_c"
        ],
        [
            "e_grid_4_c",
            "dump_zone_13"
        ],
        [
            "e_grid_4_c",
            "e_grid_4_d"
        ],
        [
            "e_grid_4_d",
            "dump_zone_14"
        ],
        [
            "e_grid_4_d",
            "e_connector_s"
        ],
        [
            "e_haul_1",
            "e_haul_2"
        ],
        [
            "e_haul_2",
            "e_haul_3"
        ],
        [
            "e_haul_3",
            "e_hub"
        ],
        [
            "e_hub",
            "e_grid_1_a"
        ],
        [
            "e_hub",
            "e_grid_3_a"
        ],
        [
            "fw_haul_1",
            "fw_haul_2"
        ],
        [
            "fw_haul_2",
            "purple_auto_fix_2"
        ],
        [
            "fw_haul_3",
            "purple_auto_fix_2"
        ],
        [
            "fw_haul_3",
            "purple_auto_fix_3"
        ],
        [
            "fw_hub",
            "fw_pit_1_a"
        ],
        [
            "fw_hub",
            "purple_auto_fix_3"
        ],
        [
            "fw_load_spur_1",
            "load_zone_4"
        ],
        [
            "fw_load_spur_10",
            "load_zone_13"
        ],
        [
            "fw_load_spur_11",
            "load_zone_14"
        ],
        [
            "fw_load_spur_12",
            "load_zone_15"
        ],
        [
            "fw_load_spur_2",
            "load_zone_5"
        ],
        [
            "fw_load_spur_3",
            "load_zone_6"
        ],
        [
            "fw_load_spur_4",
            "load_zone_7"
        ],
        [
            "fw_load_spur_5",
            "load_zone_8"
        ],
        [
            "fw_load_spur_6",
            "load_zone_9"
        ],
        [
            "fw_load_spur_7",
            "load_zone_10"
        ],
        [
            "fw_load_spur_8",
            "load_zone_11"
        ],
        [
            "fw_load_spur_9",
            "load_zone_12"
        ],
        [
            "fw_pit_1_a",
            "fw_pit_1_b"
        ],
        [
            "fw_pit_1_a",
            "fw_pit_2_a"
        ],
        [
            "fw_pit_1_b",
            "fw_load_spur_1"
        ],
        [
            "fw_pit_1_b",
            "fw_pit_1_c"
        ],
        [
            "fw_pit_1_c",
            "fw_load_spur_2"
        ],
        [
            "fw_pit_1_c",
            "fw_pit_1_d"
        ],
        [
            "fw_pit_1_d",
            "fw_load_spur_3"
        ],
        [
            "fw_pit_1_d",
            "fw_pit_1_e"
        ],
        [
            "fw_pit_1_e",
            "fw_pit_1_f"
        ],
        [
            "fw_pit_1_e",
            "fw_pit_2_e"
        ],
        [
            "fw_pit_1_f",
            "fw_load_spur_4"
        ],
        [
            "fw_pit_1_f",
            "purple_auto_fix_3"
        ],
        [
            "fw_pit_1_g",
            "fw_pit_1_a"
        ],
        [
            "fw_pit_1_g",
            "fw_pit_2_g"
        ],
        [
            "fw_pit_1_g",
            "purple_auto_fix_3"
        ],
        [
            "fw_pit_2_a",
            "fw_pit_2_b"
        ],
        [
            "fw_pit_2_a",
            "fw_pit_3_a"
        ],
        [
            "fw_pit_2_b",
            "fw_load_spur_5"
        ],
        [
            "fw_pit_2_b",
            "fw_pit_2_c"
        ],
        [
            "fw_pit_2_c",
            "fw_load_spur_6"
        ],
        [
            "fw_pit_2_c",
            "fw_pit_2_d"
        ],
        [
            "fw_pit_2_d",
            "fw_load_spur_7"
        ],
        [
            "fw_pit_2_d",
            "fw_pit_2_e"
        ],
        [
            "fw_pit_2_e",
            "fw_pit_2_f"
        ],
        [
            "fw_pit_2_e",
            "fw_pit_3_e"
        ],
        [
            "fw_pit_2_f",
            "fw_load_spur_8"
        ],
        [
            "fw_pit_2_f",
            "fw_pit_2_g"
        ],
        [
            "fw_pit_2_g",
            "fw_pit_2_a"
        ],
        [
            "fw_pit_2_g",
            "fw_pit_3_g"
        ],
        [
            "fw_pit_3_a",
            "fw_pit_3_b"
        ],
        [
            "fw_pit_3_b",
            "fw_load_spur_9"
        ],
        [
            "fw_pit_3_b",
            "fw_pit_3_c"
        ],
        [
            "fw_pit_3_c",
            "fw_load_spur_10"
        ],
        [
            "fw_pit_3_c",
            "fw_pit_3_d"
        ],
        [
            "fw_pit_3_d",
            "fw_load_spur_11"
        ],
        [
            "fw_pit_3_d",
            "fw_pit_3_e"
        ],
        [
            "fw_pit_3_e",
            "fw_pit_3_f"
        ],
        [
            "fw_pit_3_f",
            "fw_load_spur_12"
        ],
        [
            "fw_pit_3_f",
            "purple_auto_fix_2"
        ],
        [
            "fw_pit_3_g",
            "fw_pit_3_a"
        ],
        [
            "fw_pit_3_g",
            "purple_auto_fix_2"
        ],
        [
            "ix_east_1",
            "ix_east_2"
        ],
        [
            "ix_east_2",
            "dump_hub_1b"
        ],
        [
            "ix_east_2",
            "e_haul_1"
        ],
        [
            "ix_east_2",
            "load_hub_2b"
        ],
        [
            "ix_north_1",
            "ix_north_2"
        ],
        [
            "ix_north_2",
            "load_hub_1a"
        ],
        [
            "ix_north_2",
            "load_hub_2a"
        ],
        [
            "ix_north_2",
            "n_haul_1"
        ],
        [
            "ix_west_1",
            "ix_west_2"
        ],
        [
            "ix_west_2",
            "connector_1_3"
        ],
        [
            "ix_west_2",
            "fw_haul_1"
        ],
        [
            "ix_west_2",
            "load_hub_1b"
        ],
        [
            "load_hub_1a",
            "load_hub_1b"
        ],
        [
            "load_hub_1b",
            "load_spur_1a_1"
        ],
        [
            "load_hub_1b",
            "load_spur_1b_1"
        ],
        [
            "load_hub_1b",
            "purple_auto_fix_1"
        ],
        [
            "load_hub_2a",
            "load_hub_2b"
        ],
        [
            "load_hub_2b",
            "load_spur_2a_1"
        ],
        [
            "load_hub_2b",
            "load_spur_2b_1"
        ],
        [
            "load_spur_1a_1",
            "load_spur_1a_2"
        ],
        [
            "load_spur_1a_2",
            "purple_auto_fix_1"
        ],
        [
            "load_spur_1b_1",
            "load_spur_1b_2"
        ],
        [
            "load_spur_1b_2",
            "load_zone_2"
        ],
        [
            "load_spur_2a_1",
            "load_spur_2a_2"
        ],
        [
            "load_spur_2a_2",
            "load_zone_3"
        ],
        [
            "load_spur_2b_1",
            "load_spur_2b_2"
        ],
        [
            "load_spur_2b_2",
            "load_zone_3"
        ],
        [
            "load_zone_1",
            "purple_auto_fix_1"
        ],
        [
            "load_zone_3",
            "connector_1_1"
        ],
        [
            "main_hub",
            "dump_hub_1a"
        ],
        [
            "main_hub",
            "ix_east_1"
        ],
        [
            "main_hub",
            "ix_north_1"
        ],
        [
            "main_hub",
            "ix_west_1"
        ],
        [
            "main_hub",
            "sw_haul_1"
        ],
        [
            "n_haul_1",
            "n_haul_2"
        ],
        [
            "n_haul_2",
            "n_haul_3"
        ],
        [
            "n_haul_3",
            "n_hub"
        ],
        [
            "n_hub",
            "n_q_1_a"
        ],
        [
            "n_load_spur_1",
            "load_zone_16"
        ],
        [
            "n_load_spur_2",
            "load_zone_17"
        ],
        [
            "n_load_spur_3",
            "load_zone_18"
        ],
        [
            "n_load_spur_4",
            "load_zone_19"
        ],
        [
            "n_load_spur_5",
            "load_zone_20"
        ],
        [
            "n_load_spur_6",
            "load_zone_21"
        ],
        [
            "n_q_1_a",
            "n_q_1_b"
        ],
        [
            "n_q_1_a",
            "n_q_2_a"
        ],
        [
            "n_q_1_b",
            "n_load_spur_1"
        ],
        [
            "n_q_1_b",
            "n_q_1_c"
        ],
        [
            "n_q_1_c",
            "n_load_spur_2"
        ],
        [
            "n_q_1_c",
            "n_q_1_d"
        ],
        [
            "n_q_1_d",
            "n_q_1_e"
        ],
        [
            "n_q_1_e",
            "n_load_spur_3"
        ],
        [
            "n_q_1_e",
            "n_q_1_f"
        ],
        [
            "n_q_1_f",
            "n_hub"
        ],
        [
            "n_q_2_a",
            "n_q_2_b"
        ],
        [
            "n_q_2_b",
            "n_load_spur_4"
        ],
        [
            "n_q_2_b",
            "n_q_2_c"
        ],
        [
            "n_q_2_c",
            "n_load_spur_5"
        ],
        [
            "n_q_2_c",
            "n_q_2_d"
        ],
        [
            "n_q_2_d",
            "n_q_2_e"
        ],
        [
            "n_q_2_e",
            "n_load_spur_6"
        ],
        [
            "n_q_2_e",
            "n_q_2_f"
        ],
        [
            "n_q_2_f",
            "n_q_1_f"
        ],
        [
            "ne_haul_1",
            "ne_haul_2"
        ],
        [
            "ne_haul_2",
            "ne_hub"
        ],
        [
            "ne_hub",
            "ne_q_1_a"
        ],
        [
            "ne_load_spur_1",
            "load_zone_24"
        ],
        [
            "ne_load_spur_2",
            "load_zone_25"
        ],
        [
            "ne_load_spur_3",
            "load_zone_26"
        ],
        [
            "ne_load_spur_4",
            "load_zone_27"
        ],
        [
            "ne_load_spur_5",
            "load_zone_28"
        ],
        [
            "ne_load_spur_6",
            "load_zone_29"
        ],
        [
            "ne_q_1_a",
            "ne_q_1_b"
        ],
        [
            "ne_q_1_a",
            "ne_q_2_a"
        ],
        [
            "ne_q_1_b",
            "ne_load_spur_1"
        ],
        [
            "ne_q_1_b",
            "ne_q_1_c"
        ],
        [
            "ne_q_1_c",
            "ne_load_spur_2"
        ],
        [
            "ne_q_1_c",
            "ne_q_1_d"
        ],
        [
            "ne_q_1_d",
            "ne_q_1_e"
        ],
        [
            "ne_q_1_e",
            "ne_load_spur_3"
        ],
        [
            "ne_q_1_e",
            "ne_q_1_f"
        ],
        [
            "ne_q_1_f",
            "ne_hub"
        ],
        [
            "ne_q_2_a",
            "ne_q_2_b"
        ],
        [
            "ne_q_2_b",
            "ne_load_spur_4"
        ],
        [
            "ne_q_2_b",
            "ne_q_2_c"
        ],
        [
            "ne_q_2_c",
            "ne_load_spur_5"
        ],
        [
            "ne_q_2_c",
            "ne_q_2_d"
        ],
        [
            "ne_q_2_d",
            "ne_q_2_e"
        ],
        [
            "ne_q_2_e",
            "ne_load_spur_6"
        ],
        [
            "ne_q_2_e",
            "ne_q_2_f"
        ],
        [
            "ne_q_2_f",
            "ne_q_1_f"
        ],
        [
            "s_connector_1",
            "s_connector_2"
        ],
        [
            "s_connector_2",
            "sw_hub"
        ],
        [
            "s_dump_spur_1",
            "dump_zone_15"
        ],
        [
            "s_dump_spur_2",
            "dump_zone_16"
        ],
        [
            "s_dump_spur_3",
            "dump_zone_17"
        ],
        [
            "s_dump_spur_4",
            "dump_zone_18"
        ],
        [
            "s_dump_spur_5",
            "dump_zone_19"
        ],
        [
            "s_dump_spur_6",
            "dump_zone_20"
        ],
        [
            "s_dump_spur_7",
            "dump_zone_21"
        ],
        [
            "s_haul_1",
            "s_haul_2"
        ],
        [
            "s_haul_2",
            "s_haul_3"
        ],
        [
            "s_haul_3",
            "s_connector_1"
        ],
        [
            "s_haul_3",
            "s_hub"
        ],
        [
            "s_hub",
            "s_sp_1_a"
        ],
        [
            "s_sp_1_a",
            "s_sp_1_b"
        ],
        [
            "s_sp_1_a",
            "s_sp_2_a"
        ],
        [
            "s_sp_1_b",
            "s_dump_spur_1"
        ],
        [
            "s_sp_1_b",
            "s_sp_1_c"
        ],
        [
            "s_sp_1_c",
            "s_dump_spur_2"
        ],
        [
            "s_sp_1_c",
            "s_sp_1_d"
        ],
        [
            "s_sp_1_d",
            "s_sp_1_e"
        ],
        [
            "s_sp_1_e",
            "s_dump_spur_3"
        ],
        [
            "s_sp_1_e",
            "s_sp_1_f"
        ],
        [
            "s_sp_1_f",
            "s_hub"
        ],
        [
            "s_sp_2_a",
            "s_sp_2_b"
        ],
        [
            "s_sp_2_b",
            "s_dump_spur_4"
        ],
        [
            "s_sp_2_b",
            "s_sp_2_c"
        ],
        [
            "s_sp_2_c",
            "s_sp_2_d"
        ],
        [
            "s_sp_2_d",
            "s_dump_spur_5"
        ],
        [
            "s_sp_2_d",
            "s_sp_2_e"
        ],
        [
            "s_sp_2_e",
            "s_dump_spur_6"
        ],
        [
            "s_sp_2_e",
            "s_sp_2_f"
        ],
        [
            "s_sp_2_f",
            "s_sp_2_g"
        ],
        [
            "s_sp_2_g",
            "s_dump_spur_7"
        ],
        [
            "s_sp_2_g",
            "s_sp_2_h"
        ],
        [
            "s_sp_2_h",
            "s_sp_1_f"
        ],
        [
            "service_exit_1",
            "service_exit_2"
        ],
        [
            "service_exit_2",
            "main_hub"
        ],
        [
            "service_haul_1",
            "service_haul_2"
        ],
        [
            "service_haul_2",
            "service_hub"
        ],
        [
            "service_hub",
            "service_loop_1"
        ],
        [
            "service_hub",
            "service_loop_6"
        ],
        [
            "service_loop_1",
            "service_loop_2"
        ],
        [
            "service_loop_2",
            "parking_1"
        ],
        [
            "service_loop_2",
            "parking_2"
        ],
        [
            "service_loop_2",
            "service_loop_3"
        ],
        [
            "service_loop_3",
            "service_loop_4"
        ],
        [
            "service_loop_5",
            "fuel_1"
        ],
        [
            "service_loop_5",
            "fuel_2"
        ],
        [
            "service_loop_5",
            "service_loop_4"
        ],
        [
            "service_loop_6",
            "service_loop_5"
        ],
        [
            "start_zone",
            "service_exit_1"
        ],
        [
            "sw_connector_1",
            "sw_haul_3"
        ],
        [
            "sw_connector_2",
            "sw_haul_3"
        ],
        [
            "sw_dump_spur_1",
            "dump_zone_22"
        ],
        [
            "sw_dump_spur_2",
            "dump_zone_23"
        ],
        [
            "sw_dump_spur_3",
            "dump_zone_24"
        ],
        [
            "sw_haul_1",
            "sw_haul_2"
        ],
        [
            "sw_haul_2",
            "sw_haul_3"
        ],
        [
            "sw_haul_3",
            "sw_hub"
        ],
        [
            "sw_hub",
            "sw_dump_spur_1"
        ],
        [
            "sw_hub",
            "sw_dump_spur_2"
        ],
        [
            "sw_hub",
            "sw_dump_spur_3"
        ],
        [
            "sw_hub",
            "sw_load_spur_1"
        ],
        [
            "sw_hub",
            "sw_load_spur_2"
        ],
        [
            "sw_load_spur_1",
            "load_zone_22"
        ],
        [
            "sw_load_spur_2",
            "load_zone_23"
        ]
    ],
    "LOAD_ZONES": [
        "load_zone_1",
        "load_zone_10",
        "load_zone_11",
        "load_zone_12",
        "load_zone_13",
        "load_zone_14",
        "load_zone_15",
        "load_zone_16",
        "load_zone_17",
        "load_zone_18",
        "load_zone_19",
        "load_zone_2",
        "load_zone_20",
        "load_zone_21",
        "load_zone_22",
        "load_zone_23",
        "load_zone_24",
        "load_zone_25",
        "load_zone_26",
        "load_zone_27",
        "load_zone_28",
        "load_zone_29",
        "load_zone_3",
        "load_zone_4",
        "load_zone_5",
        "load_zone_6",
        "load_zone_7",
        "load_zone_8",
        "load_zone_9"
    ],
    "DUMP_ZONES": [
        "dump_zone_1",
        "dump_zone_10",
        "dump_zone_11",
        "dump_zone_12",
        "dump_zone_13",
        "dump_zone_14",
        "dump_zone_15",
        "dump_zone_16",
        "dump_zone_17",
        "dump_zone_18",
        "dump_zone_19",
        "dump_zone_2",
        "dump_zone_20",
        "dump_zone_21",
        "dump_zone_22",
        "dump_zone_23",
        "dump_zone_24",
        "dump_zone_3",
        "dump_zone_4",
        "dump_zone_5",
        "dump_zone_6",
        "dump_zone_7",
        "dump_zone_8",
        "dump_zone_9",
        "parking_1",
        "parking_2"
    ],
    "FUEL_ZONES": [
        "fuel_1",
        "fuel_2"
    ],
    "VISUAL_ROAD_CHAINS": [
        [
            "start_zone",
            "service_exit_1",
            "service_exit_2",
            "main_hub"
        ],
        [
            "main_hub",
            "ix_west_1",
            "ix_west_2"
        ],
        [
            "main_hub",
            "ix_east_1",
            "ix_east_2"
        ],
        [
            "main_hub",
            "ix_north_1",
            "ix_north_2"
        ],
        [
            "main_hub",
            "dump_hub_1a",
            "dump_hub_1b"
        ],
        [
            "ix_west_2",
            "load_hub_1b"
        ],
        [
            "ix_north_2",
            "load_hub_1a",
            "load_hub_1b"
        ],
        [
            "ix_north_2",
            "load_hub_2a",
            "load_hub_2b"
        ],
        [
            "ix_east_2",
            "load_hub_2b"
        ],
        [
            "ix_east_2",
            "dump_hub_1b"
        ],
        [
            "connector_2_2",
            "connector_2_3",
            "dump_zone_2"
        ],
        [
            "load_hub_1b",
            "load_spur_1a_1",
            "load_spur_1a_2",
            "purple_auto_fix_1",
            "load_zone_1"
        ],
        [
            "load_hub_1b",
            "load_spur_1b_1",
            "load_spur_1b_2",
            "load_zone_2"
        ],
        [
            "load_hub_2b",
            "load_spur_2a_1",
            "load_spur_2a_2",
            "load_zone_3"
        ],
        [
            "load_hub_2b",
            "load_spur_2b_1",
            "load_spur_2b_2",
            "load_zone_3"
        ],
        [
            "dump_hub_1b",
            "dump_spur_1a_1",
            "dump_spur_1a_2",
            "dump_zone_1"
        ],
        [
            "dump_hub_1b",
            "dump_spur_1b_1",
            "dump_spur_1b_2",
            "dump_zone_2"
        ],
        [
            "load_zone_3",
            "connector_1_1",
            "connector_1_2",
            "connector_1_3",
            "purple_auto_fix_1",
            "load_hub_1b"
        ],
        [
            "ix_west_2",
            "fw_haul_1",
            "fw_haul_2",
            "purple_auto_fix_2",
            "fw_haul_3",
            "purple_auto_fix_3",
            "fw_hub"
        ],
        [
            "fw_hub",
            "fw_pit_1_a",
            "fw_pit_1_b",
            "fw_pit_1_c",
            "fw_pit_1_d",
            "fw_pit_1_e",
            "fw_pit_1_f",
            "purple_auto_fix_3",
            "fw_pit_1_g",
            "fw_pit_1_a"
        ],
        [
            "fw_pit_1_b",
            "fw_load_spur_1",
            "load_zone_4"
        ],
        [
            "fw_pit_1_c",
            "fw_load_spur_2",
            "load_zone_5"
        ],
        [
            "fw_pit_1_d",
            "fw_load_spur_3",
            "load_zone_6"
        ],
        [
            "fw_pit_1_f",
            "fw_load_spur_4",
            "load_zone_7"
        ],
        [
            "fw_pit_1_a",
            "fw_pit_2_a",
            "fw_pit_2_b",
            "fw_pit_2_c",
            "fw_pit_2_d",
            "fw_pit_2_e",
            "fw_pit_1_e"
        ],
        [
            "fw_pit_1_g",
            "fw_pit_2_g",
            "fw_pit_2_f",
            "fw_pit_2_e"
        ],
        [
            "fw_pit_2_b",
            "fw_load_spur_5",
            "load_zone_8"
        ],
        [
            "fw_pit_2_c",
            "fw_load_spur_6",
            "load_zone_9"
        ],
        [
            "fw_pit_2_d",
            "fw_load_spur_7",
            "load_zone_10"
        ],
        [
            "fw_pit_2_f",
            "fw_load_spur_8",
            "load_zone_11"
        ],
        [
            "fw_pit_2_a",
            "fw_pit_3_a",
            "fw_pit_3_b",
            "fw_pit_3_c",
            "fw_pit_3_d",
            "fw_pit_3_e",
            "fw_pit_2_e"
        ],
        [
            "fw_pit_2_g",
            "fw_pit_3_g",
            "purple_auto_fix_2",
            "fw_pit_3_f",
            "fw_pit_3_e"
        ],
        [
            "fw_pit_3_b",
            "fw_load_spur_9",
            "load_zone_12"
        ],
        [
            "fw_pit_3_c",
            "fw_load_spur_10",
            "load_zone_13"
        ],
        [
            "fw_pit_3_d",
            "fw_load_spur_11",
            "load_zone_14"
        ],
        [
            "fw_pit_3_f",
            "fw_load_spur_12",
            "load_zone_15"
        ],
        [
            "ix_north_2",
            "connector_1_1",
            "n_haul_1",
            "n_haul_2",
            "n_haul_3",
            "n_hub"
        ],
        [
            "n_hub",
            "n_q_1_a",
            "n_q_1_b",
            "n_q_1_c",
            "n_q_1_d",
            "n_q_1_e",
            "n_q_1_f",
            "n_hub"
        ],
        [
            "n_q_1_b",
            "n_load_spur_1",
            "load_zone_16"
        ],
        [
            "n_q_1_c",
            "n_load_spur_2",
            "load_zone_17"
        ],
        [
            "n_q_1_e",
            "n_load_spur_3",
            "load_zone_18"
        ],
        [
            "n_q_1_a",
            "n_q_2_a",
            "n_q_2_b",
            "n_q_2_c",
            "n_q_2_d",
            "n_q_2_e",
            "n_q_2_f",
            "n_q_1_f"
        ],
        [
            "n_q_2_b",
            "n_load_spur_4",
            "load_zone_19"
        ],
        [
            "n_q_2_c",
            "n_load_spur_5",
            "load_zone_20"
        ],
        [
            "n_q_2_e",
            "n_load_spur_6",
            "load_zone_21"
        ],
        [
            "connector_2_2",
            "e_haul_1",
            "e_haul_2",
            "e_haul_3",
            "e_hub"
        ],
        [
            "e_hub",
            "e_grid_1_a",
            "e_grid_1_b",
            "e_grid_1_c",
            "e_grid_1_d"
        ],
        [
            "e_grid_1_a",
            "e_grid_2_a"
        ],
        [
            "e_grid_1_b",
            "e_grid_2_b"
        ],
        [
            "e_grid_1_c",
            "e_grid_2_c"
        ],
        [
            "e_grid_1_d",
            "e_grid_2_d"
        ],
        [
            "e_grid_2_a",
            "e_grid_2_b",
            "e_grid_2_c",
            "e_grid_2_d"
        ],
        [
            "e_grid_1_b",
            "dump_zone_3"
        ],
        [
            "e_grid_1_c",
            "dump_zone_4"
        ],
        [
            "e_grid_1_d",
            "dump_zone_5"
        ],
        [
            "e_grid_2_b",
            "dump_zone_6"
        ],
        [
            "e_grid_2_c",
            "dump_zone_7"
        ],
        [
            "e_grid_2_d",
            "dump_zone_8"
        ],
        [
            "e_hub",
            "e_grid_3_a",
            "e_grid_3_b",
            "e_grid_3_c",
            "e_grid_3_d"
        ],
        [
            "e_grid_3_a",
            "e_grid_4_a"
        ],
        [
            "e_grid_3_b",
            "e_grid_4_b"
        ],
        [
            "e_grid_3_c",
            "e_grid_4_c"
        ],
        [
            "e_grid_3_d",
            "e_grid_4_d"
        ],
        [
            "e_grid_4_a",
            "e_grid_4_b",
            "e_grid_4_c",
            "e_grid_4_d"
        ],
        [
            "e_grid_3_b",
            "dump_zone_9"
        ],
        [
            "e_grid_3_c",
            "dump_zone_10"
        ],
        [
            "e_grid_3_d",
            "dump_zone_11"
        ],
        [
            "e_grid_4_b",
            "dump_zone_12"
        ],
        [
            "e_grid_4_c",
            "dump_zone_13"
        ],
        [
            "e_grid_4_d",
            "dump_zone_14"
        ],
        [
            "e_grid_1_d",
            "e_connector_n",
            "e_connector_s",
            "e_grid_3_d"
        ],
        [
            "e_grid_2_d",
            "e_connector_n"
        ],
        [
            "e_grid_4_d",
            "e_connector_s"
        ],
        [
            "dump_hub_1a",
            "s_haul_1",
            "s_haul_2",
            "s_haul_3",
            "s_hub"
        ],
        [
            "s_hub",
            "s_sp_1_a",
            "s_sp_1_b",
            "s_sp_1_c",
            "s_sp_1_d",
            "s_sp_1_e",
            "s_sp_1_f",
            "s_hub"
        ],
        [
            "s_sp_1_b",
            "s_dump_spur_1",
            "dump_zone_15"
        ],
        [
            "s_sp_1_c",
            "s_dump_spur_2",
            "dump_zone_16"
        ],
        [
            "s_sp_1_e",
            "s_dump_spur_3",
            "dump_zone_17"
        ],
        [
            "s_sp_1_a",
            "s_sp_2_a",
            "s_sp_2_b",
            "s_sp_2_c",
            "s_sp_2_d",
            "s_sp_2_e",
            "s_sp_2_f",
            "s_sp_2_g",
            "s_sp_2_h",
            "s_sp_1_f"
        ],
        [
            "s_sp_2_b",
            "s_dump_spur_4",
            "dump_zone_18"
        ],
        [
            "s_sp_2_d",
            "s_dump_spur_5",
            "dump_zone_19"
        ],
        [
            "s_sp_2_e",
            "s_dump_spur_6",
            "dump_zone_20"
        ],
        [
            "s_sp_2_g",
            "s_dump_spur_7",
            "dump_zone_21"
        ],
        [
            "s_haul_3",
            "s_connector_1",
            "s_connector_2"
        ],
        [
            "main_hub",
            "sw_haul_1",
            "sw_haul_2",
            "sw_haul_3",
            "sw_hub"
        ],
        [
            "sw_hub",
            "sw_dump_spur_1",
            "dump_zone_22"
        ],
        [
            "sw_hub",
            "sw_dump_spur_2",
            "dump_zone_23"
        ],
        [
            "sw_hub",
            "sw_dump_spur_3",
            "dump_zone_24"
        ],
        [
            "sw_hub",
            "sw_load_spur_1",
            "load_zone_22"
        ],
        [
            "sw_hub",
            "sw_load_spur_2",
            "load_zone_23"
        ],
        [
            "sw_connector_1",
            "sw_haul_3"
        ],
        [
            "sw_connector_2",
            "sw_haul_3"
        ],
        [
            "s_connector_2",
            "sw_hub"
        ],
        [
            "e_grid_1_a",
            "ne_haul_1"
        ],
        [
            "ne_haul_1",
            "ne_haul_2"
        ],
        [
            "ne_haul_2",
            "ne_hub"
        ],
        [
            "ne_hub",
            "ne_q_1_a"
        ],
        [
            "ne_q_1_a",
            "ne_q_1_b"
        ],
        [
            "ne_q_1_b",
            "ne_q_1_c"
        ],
        [
            "ne_q_1_c",
            "ne_q_1_d"
        ],
        [
            "ne_q_1_d",
            "ne_q_1_e"
        ],
        [
            "ne_q_1_e",
            "ne_q_1_f"
        ],
        [
            "ne_q_1_f",
            "ne_hub"
        ],
        [
            "ne_q_1_b",
            "ne_load_spur_1",
            "load_zone_24"
        ],
        [
            "ne_q_1_c",
            "ne_load_spur_2",
            "load_zone_25"
        ],
        [
            "ne_q_1_e",
            "ne_load_spur_3",
            "load_zone_26"
        ],
        [
            "ne_q_1_a",
            "ne_q_2_a"
        ],
        [
            "ne_q_2_a",
            "ne_q_2_b"
        ],
        [
            "ne_q_2_b",
            "ne_q_2_c"
        ],
        [
            "ne_q_2_c",
            "ne_q_2_d"
        ],
        [
            "ne_q_2_d",
            "ne_q_2_e"
        ],
        [
            "ne_q_2_e",
            "ne_q_2_f"
        ],
        [
            "ne_q_2_f",
            "ne_q_1_f"
        ],
        [
            "ne_q_2_b",
            "ne_load_spur_4",
            "load_zone_27"
        ],
        [
            "ne_q_2_c",
            "ne_load_spur_5",
            "load_zone_28"
        ],
        [
            "ne_q_2_e",
            "ne_load_spur_6",
            "load_zone_29"
        ],
        [
            "e_grid_4_a",
            "service_haul_1"
        ],
        [
            "service_haul_1",
            "service_haul_2"
        ],
        [
            "service_haul_2",
            "service_hub"
        ],
        [
            "service_hub",
            "service_loop_1"
        ],
        [
            "service_loop_1",
            "service_loop_2"
        ],
        [
            "service_loop_2",
            "service_loop_3"
        ],
        [
            "service_hub",
            "service_loop_6"
        ],
        [
            "service_loop_6",
            "service_loop_5"
        ],
        [
            "service_loop_5",
            "service_loop_4"
        ],
        [
            "service_loop_3",
            "service_loop_4"
        ],
        [
            "service_loop_2",
            "parking_1"
        ],
        [
            "service_loop_2",
            "parking_2"
        ],
        [
            "service_loop_5",
            "fuel_1"
        ],
        [
            "service_loop_5",
            "fuel_2"
        ],
        [
            "connector_2_2",
            "ix_east_2"
        ]
    ]
}